bmcs_beam/__init__.py
bmcs_beam/api.py
bmcs_beam/version.py
bmcs_beam/beam_config/__init__.py
bmcs_beam/beam_config/beam_design.py
bmcs_beam/beam_config/boundary_conditions.py
bmcs_beam/beam_config/system/__init__.py
bmcs_beam/beam_config/system/beam_system.py
bmcs_beam/beam_config/system/cantilever_system.py
bmcs_beam/beam_config/system/four_pb_system.py
bmcs_beam/beam_config/system/simple_dist_load_system.py
bmcs_beam/beam_config/system/system.py
bmcs_beam/beam_config/system/three_pb_system.py
bmcs_beam/beam_config/system/todo_systems.py
bmcs_beam/beam_config/system/anastruct/__init__.py
bmcs_beam/beam_config/system/anastruct/anastruct_custom_plotter.py
bmcs_beam/beam_config/system/anastruct/anastruct_testing.py
bmcs_beam/bending/__init__.py
bmcs_beam/bending/beam_sls_curve.py
bmcs_beam/bending/deflection_profile.py
bmcs_beam/bending/EC2/BoxGirder.py
bmcs_beam/bending/EC2/EC2.py
bmcs_beam/bending/EC2/GUI.py
bmcs_beam/bending/EC2/Graphics.py
bmcs_beam/bending/EC2/PSC.py
bmcs_beam/bending/EC2/RC.py
bmcs_beam/bending/EC2/TeeBeam.py
bmcs_beam/bending/EC2/Util_ACI.py
bmcs_beam/bending/EC2/Util_EC2.py
bmcs_beam/bending/EC2/Utilities.py
bmcs_beam/bending/EC2/__init__.py
bmcs_beam/mxn/__init__.py
bmcs_beam/mxn/constitutive_law.py
bmcs_beam/mxn/cross_section.py
bmcs_beam/mxn/cross_section_component.py
bmcs_beam/mxn/cross_section_state.py
bmcs_beam/mxn/ecb_calib.py
bmcs_beam/mxn/mxn_class_extension.py
bmcs_beam/mxn/mxn_class_extension_handler.py
bmcs_beam/mxn/mxn_diagram.py
bmcs_beam/mxn/mxn_tree_node.py
bmcs_beam/mxn/apps/__init__.py
bmcs_beam/mxn/apps/ex01_steel_rectangular.py
bmcs_beam/mxn/apps/ex02_spread_textile_rectangular.py
bmcs_beam/mxn/apps/ex03_uniform_rectangular.py
bmcs_beam/mxn/apps/ex04_combined_circular.py
bmcs_beam/mxn/apps/ex05_combined_I-shaped.py
bmcs_beam/mxn/apps/ex06_mxnview_cross_section.py
bmcs_beam/mxn/apps/ex07_mxnview_database.py
bmcs_beam/mxn/apps/ex08_mxnview_ecb_calib.py
bmcs_beam/mxn/apps/ex09_mxnview_prediction.py
bmcs_beam-0.0.21a0.dist-info/LICENSE
bmcs_beam-0.0.21a0.dist-info/METADATA
bmcs_beam-0.0.21a0.dist-info/WHEEL
bmcs_beam-0.0.21a0.dist-info/top_level.txt
bmcs_beam-0.0.21a0.dist-info/RECORD
