Metadata-Version: 2.1
Name: bmcs-beam
Version: 0.0.21a0
Summary: Models of brittle-matrix composite beam.
Home-page: https://github.com/bmcs-group/bmcs_beam
Author: BMCS-Group: Saeed Rastegarian, Homam Spartali, Rostislav Chudoba
Author-email: rostislav.chudoba@rwt-aachen.de
License: MIT
Classifier: License :: OSI Approved :: MIT License
Classifier: Programming Language :: Python
Classifier: Programming Language :: Python :: 3
Classifier: Programming Language :: Python :: 3.6
Classifier: Programming Language :: Python :: Implementation :: CPython
Classifier: Programming Language :: Python :: Implementation :: PyPy
Requires-Python: >=3.6.0
License-File: LICENSE
